[
    {
        "name": "La Liga",
        "slug": "la_liga",
        "api_football_id": 140,
        "country": "Spain",
        "api_football_country_id": 0
    },
    {
        "name": "Segunda Division",
        "slug": "segunda_division",
        "api_football_id": 141,
        "country": "Spain",
        "api_football_country_id": 0
    },
    {
        "name": "Bundesliga",
        "slug": "bundesliga",
        "api_football_id": 78,
        "country": "Germany",
        "api_football_country_id": 0
    },
    {
        "name": "2. Bundesliga",
        "slug": "2_bundesliga",
        "api_football_id": 79,
        "country": "Germany",
        "api_football_country_id": 0
    },
    {
        "name": "Ligue 1",
        "slug": "ligue_1",
        "api_football_id": 61,
        "country": "France",
        "api_football_country_id": 0
    },
    {
        "name": "Ligue 2",
        "slug": "ligue_2",
        "api_football_id": 62,
        "country": "France",
        "api_football_country_id": 0
    },
    {
        "name": "Super League",
        "slug": "super_league",
        "api_football_id": 207,
        "country": "Switzerland",
        "api_football_country_id": 0
    },
    {
        "name": "Challenge League",
        "slug": "challenge_league",
        "api_football_id": 208,
        "country": "Switzerland",
        "api_football_country_id": 0
    },
    {
        "name": "Primeira Liga",
        "slug": "primeira_liga",
        "api_football_id": 94,
        "country": "Portugal",
        "api_football_country_id": 0
    },
    {
        "name": "Segunda Liga",
        "slug": "segunda_liga",
        "api_football_id": 95,
        "country": "Portugal",
        "api_football_country_id": 0
    },
    {
        "name": "Eredivisie",
        "slug": "eredivisie",
        "api_football_id": 88,
        "country": "Netherlands",
        "api_football_country_id": 0
    },
    {
        "name": "Eerste Divisie",
        "slug": "eerste_divisie",
        "api_football_id": 89,
        "country": "Netherlands",
        "api_football_country_id": 0
    },
    {
        "name": "Jupiler Pro League",
        "slug": "jupiler_pro_league",
        "api_football_id": 144,
        "country": "Belgium",
        "api_football_country_id": 0
    },
    {
        "name": "Challenger Pro League",
        "slug": "challenger_pro_league",
        "api_football_id": 145,
        "country": "Belgium",
        "api_football_country_id": 0
    },
    {
        "name": "Superliga",
        "slug": "superliga",
        "api_football_id": 119,
        "country": "Denmark",
        "api_football_country_id": 0
    },
    {
        "name": "1. Division",
        "slug": "1_division",
        "api_football_id": 120,
        "country": "Denmark",
        "api_football_country_id": 0
    },
    {
        "name": "Eliteserien",
        "slug": "eliteserien",
        "api_football_id": 103,
        "country": "Norway",
        "api_football_country_id": 0
    },
    {
        "name": "1. Division",
        "slug": "1_division",
        "api_football_id": 104,
        "country": "Norway",
        "api_football_country_id": 0
    },
    {
        "name": "Allsvenskan",
        "slug": "allsvenskan",
        "api_football_id": 113,
        "country": "Sweden",
        "api_football_country_id": 0
    },
    {
        "name": "Superettan",
        "slug": "superettan",
        "api_football_id": 114,
        "country": "Sweden",
        "api_football_country_id": 0
    },
    {
        "name": "Veikkausliiga",
        "slug": "veikkausliiga",
        "api_football_id": 244,
        "country": "Finland",
        "api_football_country_id": 0
    },
    {
        "name": "Ykkönen",
        "slug": "ykkonen",
        "api_football_id": 245,
        "country": "Finland",
        "api_football_country_id": 0
    },
    {
        "name": "Ekstraklasa",
        "slug": "ekstraklasa",
        "api_football_id": 106,
        "country": "Poland",
        "api_football_country_id": 0
    },
    {
        "name": "I Liga",
        "slug": "i_liga",
        "api_football_id": 107,
        "country": "Poland",
        "api_football_country_id": 0
    },
    {
        "name": "Premier League",
        "slug": "premier_league",
        "api_football_id": 116,
        "country": "Belarus",
        "api_football_country_id": 0
    },
    // {
    //     "name": "1. Division",
    //     "slug": "1_division",
    //     "api_football_id": 117,
    //     "country": "Belarus",
    //     "api_football_country_id": 0
    // },
    {
        "name": "1 Lyga",
        "slug": "1_lyga",
        "api_football_id": 361,
        "country": "Lithuania",
        "api_football_country_id": 0
    },
    {
        "name": "A Lyga",
        "slug": "a_lyga",
        "api_football_id": 362,
        "country": "Lithuania",
        "api_football_country_id": 0
    },
    {
        "name": "1. Liga",
        "slug": "1_liga",
        "api_football_id": 364,
        "country": "Latvia",
        "api_football_country_id": 0
    },
    {
        "name": "Virsliga",
        "slug": "virsliga",
        "api_football_id": 365,
        "country": "Latvia",
        "api_football_country_id": 0
    },
    {
        "name": "Esiliiga A",
        "slug": "esiliiga_a",
        "api_football_id": 328,
        "country": "Estonia",
        "api_football_country_id": 0
    },
    {
        "name": "Meistriliiga",
        "slug": "meistriliiga",
        "api_football_id": 329,
        "country": "Estonia",
        "api_football_country_id": 0
    },
    {
        "name": "Premier League",
        "slug": "premier_league",
        "api_football_id": 235,
        "country": "Russia",
        "api_football_country_id": 0
    },
    {
        "name": "First League",
        "slug": "first_league",
        "api_football_id": 236,
        "country": "Russia",
        "api_football_country_id": 0
    },
    {
        "name": "Czech Liga",
        "slug": "czech_liga",
        "api_football_id": 345,
        "country": "Czech Republic",
        "api_football_country_id": 0
    },
    {
        "name": "FNL",
        "slug": "fnl",
        "api_football_id": 346,
        "country": "Czech Republic",
        "api_football_country_id": 0
    },
    {
        "name": "Super Liga",
        "slug": "super_liga",
        "api_football_id": 332,
        "country": "Slovakia",
        "api_football_country_id": 0
    },
    {
        "name": "2. liga",
        "slug": "2_liga",
        "api_football_id": 506,
        "country": "Slovakia",
        "api_football_country_id": 0
    },
    {
        "name": "1. SNL",
        "slug": "1_snl",
        "api_football_id": 373,
        "country": "Slovenia",
        "api_football_country_id": 0
    },
    {
        "name": "2. SNL",
        "slug": "2_snl",
        "api_football_id": 374,
        "country": "Slovenia",
        "api_football_country_id": 0
    },
    {
        "name": "NB I",
        "slug": "nb_i",
        "api_football_id": 271,
        "country": "Hungary",
        "api_football_country_id": 0
    },
    {
        "name": "NB II",
        "slug": "nb_ii",
        "api_football_id": 272,
        "country": "Hungary",
        "api_football_country_id": 0
    },
    {
        "name": "Liga I",
        "slug": "liga_1",
        "api_football_id": 283,
        "country": "Romania",
        "api_football_country_id": 0
    },
    {
        "name": "Liga II",
        "slug": "liga_2",
        "api_football_id": 284,
        "country": "Romania",
        "api_football_country_id": 0
    },
    {
        "name": "Super Liga",
        "slug": "super_liga",
        "api_football_id": 394,
        "country": "Moldova",
        "api_football_country_id": 0
    },
    {
        "name": "Liga 1",
        "slug": "liga_1",
        "api_football_id": 394,
        "country": "Moldova",
        "api_football_country_id": 0
    },
    {
        "name": "First League",
        "slug": "first_league",
        "api_football_id": 172,
        "country": "Bulgaria",
        "api_football_country_id": 0
    },
    {
        "name": "Second League",
        "slug": "second_league",
        "api_football_id": 173,
        "country": "Bulgaria",
        "api_football_country_id": 0
    },
    {
        "name": "HNL",
        "slug": "hnl",
        "api_football_id": 210,
        "country": "Croatia",
        "api_football_country_id": 0
    },
    {
        "name": "First NL",
        "slug": "first_nl",
        "api_football_id": 211,
        "country": "Croatia",
        "api_football_country_id": 0
    },
    {
        "name": "Prva Liga",
        "slug": "prva_liga",
        "api_football_id": 287,
        "country": "Serbia",
        "api_football_country_id": 0
    },
    {
        "name": "Super Liga",
        "slug": "super_liga",
        "api_football_id": 286,
        "country": "Serbia",
        "api_football_country_id": 0
    },
    {
        "name": "Premijer Liga",
        "slug": "premijer_liga",
        "api_football_id": 315,
        "country": "Bosnia and Herzegovina",
        "api_football_country_id": 0
    },
    {
        "name": "1st League - FBiH",
        "slug": "1st_league_fbih",
        "api_football_id": 316,
        "country": "Bosnia and Herzegovina",
        "api_football_country_id": 0
    },
    {
        "name": "First League",
        "slug": "first_league",
        "api_football_id": 355,
        "country": "Montenegro",
        "api_football_country_id": 0
    },
    {
        "name": "Second League",
        "slug": "second_league",
        "api_football_id": 356,
        "country": "Montenegro",
        "api_football_country_id": 0
    },
    {
        "name": "Superliga",
        "slug": "superliga",
        "api_football_id": 310,
        "country": "Albania",
        "api_football_country_id": 0
    },
    {
        "name": "1st Division",
        "slug": "1st_division",
        "api_football_id": 311,
        "country": "Albania",
        "api_football_country_id": 0
    },
    {
        "name": "Superliga",
        "slug": "superliga",
        "api_football_id": 664,
        "country": "Kosovo",
        "api_football_country_id": 0
    },
    {
        "name": "First League",
        "slug": "first_league",
        "api_football_id": 317,
        "country": "Macedonia",
        "api_football_country_id": 0
    },
    {
        "name": "Premier League",
        "slug": "premier_league",
        "api_football_id": 393,
        "country": "Malta",
        "api_football_country_id": 0
    },
    {
        "name": "Challenge League",
        "slug": "challenge_league",
        "api_football_id": 392,
        "country": "Malta",
        "api_football_country_id": 0
    },
    {
        "name": "Super League 1",
        "slug": "super_league_1",
        "api_football_id": 197,
        "country": "Greece",
        "api_football_country_id": 0
    },
    {
        "name": "Super League 2",
        "slug": "super_league_2",
        "api_football_id": 494,
        "country": "Greece",
        "api_football_country_id": 0
    },
    {
        "name": "1. Division",
        "slug": "1_division",
        "api_football_id": 318,
        "country": "Cyprus",
        "api_football_country_id": 0
    },
    {
        "name": "2. Division",
        "slug": "2_division",
        "api_football_id": 319,
        "country": "Cyprus",
        "api_football_country_id": 0
    },
    {
        "name": "Süper Lig",
        "slug": "super_lig",
        "api_football_id": 203,
        "country": "Turkey",
        "api_football_country_id": 0
    },
    {
        "name": "1. Lig",
        "slug": "1_lig",
        "api_football_id": 204,
        "country": "Turkey",
        "api_football_country_id": 0
    },
    {
        "name": "Serie A",
        "slug": "serie_a",
        "api_football_id": 135,
        "country": "Italy",
        "api_football_country_id": 0
    },
    {
        "name": "Serie B",
        "slug": "serie_b",
        "api_football_id": 136,
        "country": "Italy",
        "api_football_country_id": 0
    },
    {
        "name": "Premier Division",
        "slug": "premier_division",
        "api_football_id": 357,
        "country": "Ireland",
        "api_football_country_id": 0
    },
    {
        "name": "First Division",
        "slug": "first_division",
        "api_football_id": 358,
        "country": "Ireland",
        "api_football_country_id": 0
    },
    {
        "name": "Premiership",
        "slug": "premiership",
        "api_football_id": 179,
        "country": "Scotland",
        "api_football_country_id": 0
    },
    {
        "name": "Championship",
        "slug": "championship",
        "api_football_id": 180,
        "country": "Scotland",
        "api_football_country_id": 0
    },
    {
        "name": "Premiership",
        "slug": "premiership",
        "api_football_id": 408,
        "country": "Northern Ireland",
        "api_football_country_id": 0
    },
    {
        "name": "Championship",
        "slug": "championship",
        "api_football_id": 407,
        "country": "Northern Ireland",
        "api_football_country_id": 0
    },
    {
        "name": "Premier League",
        "slug": "premier_league",
        "api_football_id": 39,
        "country": "England",
        "api_football_country_id": 0
    },
    {
        "name": "Championship",
        "slug": "championship",
        "api_football_id": 40,
        "country": "England",
        "api_football_country_id": 0
    },
    {
        "name": "Ligat Ha'al",
        "slug": "ligat_ha_al",
        "api_football_id": 383,
        "country": "Israel",
        "api_football_country_id": 0
    },
    {
        "name": "Liga Leumit",
        "slug": "liga_leumit",
        "api_football_id": 382,
        "country": "Israel",
        "api_football_country_id": 0
    },
    {
        "name": "Erovnuli Liga",
        "slug": "erovnuli_liga",
        "api_football_id": 327,
        "country": "Georgia",
        "api_football_country_id": 0
    },
    {
        "name": "Erovnuli Liga 2",
        "slug": "erovnuli_liga_2",
        "api_football_id": 326,
        "country": "Georgia",
        "api_football_country_id": 0
    },
    {
        "name": "National Division",
        "slug": "national_division",
        "api_football_id": 261,
        "country": "Luxembourg",
        "api_football_country_id": 0
    },
    {
        "name": "Úrvalsdeild",
        "slug": "urvalsdeild",
        "api_football_id": 164,
        "country": "Iceland",
        "api_football_country_id": 0
    },
    {
        "name": "1. Deild",
        "slug": "1_deild",
        "api_football_id": 165,
        "country": "Iceland",
        "api_football_country_id": 0
    },
    {
        "name": "Premier League",
        "slug": "premier_league",
        "api_football_id": 389,
        "country": "Kazakhstan",
        "api_football_country_id": 0
    },
    {
        "name": "1. Division",
        "slug": "1_division",
        "api_football_id": 388,
        "country": "Kazakhstan",
        "api_football_country_id": 0
    },
    {
        "name": "Premier League",
        "slug": "premier_league",
        "api_football_id": 333,
        "country": "Ukraine",
        "api_football_country_id": 0
    },
    {
        "name": "Persha Liga",
        "slug": "persha_liga",
        "api_football_id": 334,
        "country": "Ukraine",
        "api_football_country_id": 0
    },
    {
        "name": "",
        "slug": "",
        "api_football_id": 0,
        "country": "",
        "api_football_country_id": 0
    },
    {
        "name": "",
        "slug": "",
        "api_football_id": 0,
        "country": "",
        "api_football_country_id": 0
    }
]